mo_sql/__init__.py
mo_sql/utils.py
mo_sql-4.679.25061.dist-info/LICENSE
mo_sql-4.679.25061.dist-info/METADATA
mo_sql-4.679.25061.dist-info/WHEEL
mo_sql-4.679.25061.dist-info/top_level.txt
mo_sql-4.679.25061.dist-info/RECORD
