Metadata-Version: 2.2
Name: mo-sql
Version: 4.679.25061
Summary: More SQL!  For safely assembling SQL
Home-page: https://github.com/klahnakoski/mo-sql
Author: Kyle Lahnakoski
Author-email: kyle@lahnakoski.com
License: MPL 2.0
Classifier: Development Status :: 4 - Beta
Classifier: Topic :: Software Development :: Libraries
Classifier: Topic :: Software Development :: Libraries :: Python Modules
Classifier: License :: OSI Approved :: Mozilla Public License 2.0 (MPL 2.0)
Classifier: Topic :: Database
Classifier: Topic :: Utilities
Classifier: Programming Language :: SQL
Classifier: Programming Language :: Python :: 3.8
Classifier: Programming Language :: Python :: 3.9
Classifier: Programming Language :: Python :: 3.10
Classifier: Programming Language :: Python :: 3.11
Classifier: Programming Language :: Python :: 3.12
Classifier: Programming Language :: Python :: 3.13
License-File: LICENSE
Requires-Dist: mo-dots==10.678.25061
Requires-Dist: mo-future==7.678.25061
Requires-Dist: mo-json==6.679.25061
Requires-Dist: mo-logs==8.678.25061
Provides-Extra: tests
Requires-Dist: mo-testing>=8.667.25032; extra == "tests"
Dynamic: author
Dynamic: author-email
Dynamic: classifier
Dynamic: description
Dynamic: description-content-type
Dynamic: home-page
Dynamic: license
Dynamic: provides-extra
Dynamic: requires-dist
Dynamic: summary
